README.rst
setup.py
django_jsgettext.egg-info/PKG-INFO
django_jsgettext.egg-info/SOURCES.txt
django_jsgettext.egg-info/dependency_links.txt
django_jsgettext.egg-info/not-zip-safe
django_jsgettext.egg-info/top_level.txt
djsgettext/__init__.py
djsgettext/views.py
djsgettext/management/__init__.py
djsgettext/management/commands/__init__.py
djsgettext/management/commands/jsgettext_makemessages.py