Metadata-Version: 1.1
Name: django-jsgettext
Version: 0.5
Summary: Improved and complement gettext support for javascript for Django
Home-page: https://github.com/niwibe/django-jsgettext
Author: Andrey Antukh
Author-email: niwi@niwi.be
License: BSD
Platform: OS Independent
Classifier: Development Status :: 4 - Beta
Classifier: Framework :: Django
Classifier: Intended Audience :: Developers
Classifier: License :: OSI Approved :: BSD License
Classifier: Operating System :: OS Independent
Classifier: Programming Language :: Python
Classifier: Topic :: Internet :: WWW/HTTP
